partipy/__init__.py
partipy/_docs.py
partipy/arch.py
partipy/coreset.py
partipy/crosstalk.py
partipy/datasets.py
partipy/decomposition.py
partipy/enrichment.py
partipy/initialize.py
partipy/io.py
partipy/optim.py
partipy/paretoti.py
partipy/plotting.py
partipy/schema.py
partipy/selection.py
partipy/simulate.py
partipy/utils.py
partipy/weights.py
partipy-0.1.0.dist-info/METADATA
partipy-0.1.0.dist-info/WHEEL
partipy-0.1.0.dist-info/licenses/LICENSE
partipy-0.1.0.dist-info/RECORD
