Metadata-Version: 2.4
Name: partipy
Version: 0.1.0
Summary: Pareto Task Inference in Python
Project-URL: Homepage, https://github.com/saezlab/partipy
Project-URL: Source, https://github.com/saezlab/partipy
Project-URL: Bug, https://github.com/saezlab/partipy/issues
Project-URL: Changelog, https://github.com/saezlab/partipy/CHANGELOG.md
Project-URL: Documentation, https://partipy.readthedocs.io/en/latest/
Author-email: Philipp Sven Lars Schäfer <philipp.schaefer@uni-heidelberg.de>, Leoni Zimmermann <leoni.zimmermann@stud.uni-heidelberg.de>
License:                     GNU GENERAL PUBLIC LICENSE
License-File: LICENSE
Classifier: Programming Language :: Python :: 3 :: Only
Classifier: Programming Language :: Python :: 3.10
Classifier: Programming Language :: Python :: 3.11
Classifier: Programming Language :: Python :: 3.12
Requires-Python: >=3.10
Requires-Dist: dcor
Requires-Dist: decoupler>=2.0.0
Requires-Dist: joblib
Requires-Dist: matplotlib
Requires-Dist: nbformat
Requires-Dist: numba
Requires-Dist: numpy
Requires-Dist: pandas
Requires-Dist: plotly
Requires-Dist: plotnine
Requires-Dist: pydantic
Requires-Dist: scanpy
Requires-Dist: scipy
Requires-Dist: tqdm
Provides-Extra: dev
Requires-Dist: mypy; extra == 'dev'
Requires-Dist: pandas-stubs; extra == 'dev'
Requires-Dist: pre-commit; extra == 'dev'
Requires-Dist: ruff; extra == 'dev'
Requires-Dist: twine>=4.0.2; extra == 'dev'
Requires-Dist: types-tqdm; extra == 'dev'
Provides-Extra: doc
Requires-Dist: docutils!=0.18.*,!=0.19.*,>=0.8; extra == 'doc'
Requires-Dist: ipykernel; extra == 'doc'
Requires-Dist: ipython; extra == 'doc'
Requires-Dist: jupyter; extra == 'doc'
Requires-Dist: liana; extra == 'doc'
Requires-Dist: myst-nb>=1.1; extra == 'doc'
Requires-Dist: networkx; extra == 'doc'
Requires-Dist: pybiomart; extra == 'doc'
Requires-Dist: requests; extra == 'doc'
Requires-Dist: session-info2; extra == 'doc'
Requires-Dist: setuptools; extra == 'doc'
Requires-Dist: sphinx-autodoc-typehints; extra == 'doc'
Requires-Dist: sphinx-book-theme>=1; extra == 'doc'
Requires-Dist: sphinx-copybutton; extra == 'doc'
Requires-Dist: sphinx-tabs; extra == 'doc'
Requires-Dist: sphinx>=4; extra == 'doc'
Requires-Dist: sphinxcontrib-bibtex>=1; extra == 'doc'
Requires-Dist: sphinxext-opengraph; extra == 'doc'
Requires-Dist: squidpy; extra == 'doc'
Provides-Extra: extra
Requires-Dist: liana; extra == 'extra'
Requires-Dist: networkx; extra == 'extra'
Requires-Dist: pybiomart; extra == 'extra'
Requires-Dist: requests; extra == 'extra'
Requires-Dist: session-info2; extra == 'extra'
Requires-Dist: squidpy; extra == 'extra'
Provides-Extra: test
Requires-Dist: coverage; extra == 'test'
Requires-Dist: hypothesis; extra == 'test'
Requires-Dist: ipytest; extra == 'test'
Requires-Dist: liana; extra == 'test'
Requires-Dist: networkx; extra == 'test'
Requires-Dist: pybiomart; extra == 'test'
Requires-Dist: pyqt5; extra == 'test'
Requires-Dist: pytest; extra == 'test'
Requires-Dist: pytest-cov; extra == 'test'
Requires-Dist: pytest-qt; extra == 'test'
Requires-Dist: pytest-randomly; extra == 'test'
Requires-Dist: pytest-xvfb; extra == 'test'
Requires-Dist: requests; extra == 'test'
Requires-Dist: session-info2; extra == 'test'
Requires-Dist: squidpy; extra == 'test'
Requires-Dist: tomli>=2.0.1; (python_version < '3.11') and extra == 'test'
